pydantic_ai_backends/__init__.py
pydantic_ai_backends/composite.py
pydantic_ai_backends/filesystem.py
pydantic_ai_backends/protocol.py
pydantic_ai_backends/runtimes.py
pydantic_ai_backends/sandbox.py
pydantic_ai_backends/session.py
pydantic_ai_backends/state.py
pydantic_ai_backends/types.py
pydantic_ai_backend-0.0.3.dist-info/METADATA
pydantic_ai_backend-0.0.3.dist-info/WHEEL
pydantic_ai_backend-0.0.3.dist-info/licenses/LICENSE
pydantic_ai_backend-0.0.3.dist-info/RECORD
