Metadata-Version: 2.4
Name: pydantic-ai-backend
Version: 0.0.3
Summary: File storage and sandbox backends for AI agents
Project-URL: Homepage, https://github.com/vstorm-co/pydantic-ai-backend
Project-URL: Repository, https://github.com/vstorm-co/pydantic-ai-backend
Project-URL: Issues, https://github.com/vstorm-co/pydantic-ai-backend/issues
Author: VStorm
License-Expression: MIT
License-File: LICENSE
Classifier: Development Status :: 4 - Beta
Classifier: Intended Audience :: Developers
Classifier: License :: OSI Approved :: MIT License
Classifier: Operating System :: OS Independent
Classifier: Programming Language :: Python
Classifier: Programming Language :: Python :: 3
Classifier: Programming Language :: Python :: 3.10
Classifier: Programming Language :: Python :: 3.11
Classifier: Programming Language :: Python :: 3.12
Classifier: Programming Language :: Python :: 3.13
Classifier: Topic :: Software Development :: Libraries :: Python Modules
Classifier: Typing :: Typed
Requires-Python: >=3.10
Requires-Dist: pydantic>=2.0
Requires-Dist: wcmatch>=8.0
Provides-Extra: dev
Requires-Dist: build>=1.0.0; extra == 'dev'
Requires-Dist: coverage>=7.0.0; extra == 'dev'
Requires-Dist: mypy>=1.0.0; extra == 'dev'
Requires-Dist: pre-commit>=4.0.0; extra == 'dev'
Requires-Dist: pyright>=1.1.400; extra == 'dev'
Requires-Dist: pytest-asyncio>=0.23.0; extra == 'dev'
Requires-Dist: pytest-cov>=7.0.0; extra == 'dev'
Requires-Dist: pytest>=9.0.0; extra == 'dev'
Requires-Dist: ruff>=0.8.0; extra == 'dev'
Provides-Extra: docker
Requires-Dist: chardet>=5.2.0; extra == 'docker'
Requires-Dist: docker>=7.0; extra == 'docker'
Requires-Dist: pypdf>=5.1.0; extra == 'docker'
